{
    "subsonic-response": {
        "status": "ok",
        "version": "1.16.1",
        "type": "ampache",
        "serverVersion": "7.6.0",
        "openSubsonic": true,
        "playlists": {
            "playlist": [
                {
                    "id": "sp-21",
                    "name": "admin - 02/23/2021 14:36:44 (admin)",
                    "owner": "admin",
                    "public": true,
                    "songCount": 0,
                    "duration": 0,
                    "created": "1970-01-01T00:00:00+00:00",
                    "changed": "2025-07-01T05:51:53+00:00"
                },
                {
                    "id": "sp-14",
                    "name": "Album 1* (System)",
                    "owner": "System",
                    "public": true,
                    "songCount": 2,
                    "duration": 600,
                    "created": "1970-01-01T00:00:00+00:00",
                    "changed": "2025-07-01T05:51:53+00:00"
                },
                {
                    "id": "sp-13",
                    "name": "Album 2* (System)",
                    "owner": "System",
                    "public": true,
                    "songCount": 11,
                    "duration": 4423,
                    "created": "1970-01-01T00:00:00+00:00",
                    "changed": "2025-07-01T05:51:53+00:00"
                },
                {
                    "id": "sp-12",
                    "name": "Album 3* (System)",
                    "owner": "System",
                    "public": true,
                    "songCount": 0,
                    "duration": 0,
                    "created": "1970-01-01T00:00:00+00:00",
                    "changed": "2025-07-01T05:51:53+00:00"
                },
                {
                    "id": "sp-11",
                    "name": "Album 4* (System)",
                    "owner": "System",
                    "public": true,
                    "songCount": 0,
                    "duration": 0,
                    "created": "1970-01-01T00:00:00+00:00",
                    "changed": "2025-07-01T05:51:53+00:00"
                },
                {
                    "id": "sp-10",
                    "name": "Album 5* (System)",
                    "owner": "System",
                    "public": true,
                    "songCount": 0,
                    "duration": 0,
                    "created": "1970-01-01T00:00:00+00:00",
                    "changed": "2025-07-01T05:51:53+00:00"
                },
                {
                    "id": "sp-9",
                    "name": "Artist 1* (System)",
                    "owner": "System",
                    "public": true,
                    "songCount": 0,
                    "duration": 0,
                    "created": "1970-01-01T00:00:00+00:00",
                    "changed": "2025-07-01T05:51:53+00:00"
                },
                {
                    "id": "sp-8",
                    "name": "Artist 2* (System)",
                    "owner": "System",
                    "public": true,
                    "songCount": 0,
                    "duration": 0,
                    "created": "1970-01-01T00:00:00+00:00",
                    "changed": "2025-07-01T05:51:53+00:00"
                },
                {
                    "id": "sp-7",
                    "name": "Artist 3* (System)",
                    "owner": "System",
                    "public": true,
                    "songCount": 0,
                    "duration": 0,
                    "created": "1970-01-01T00:00:00+00:00",
                    "changed": "2025-07-01T05:51:53+00:00"
                },
                {
                    "id": "sp-6",
                    "name": "Artist 4* (System)",
                    "owner": "System",
                    "public": true,
                    "songCount": 0,
                    "duration": 0,
                    "created": "1970-01-01T00:00:00+00:00",
                    "changed": "2025-07-01T05:51:53+00:00"
                },
                {
                    "id": "sp-5",
                    "name": "Artist 5* (System)",
                    "owner": "System",
                    "public": true,
                    "songCount": 0,
                    "duration": 0,
                    "created": "1970-01-01T00:00:00+00:00",
                    "changed": "2025-07-01T05:51:53+00:00"
                },
                {
                    "id": "pl-65",
                    "name": "Nofi",
                    "owner": "user",
                    "public": true,
                    "songCount": 11,
                    "duration": 4423,
                    "created": "2025-06-30T06:42:39+00:00",
                    "changed": "2025-06-30T06:42:39+00:00"
                },
                {
                    "id": "pl-3",
                    "name": "random - admin - private (admin)",
                    "owner": "admin",
                    "public": false,
                    "songCount": 43,
                    "duration": 17875,
                    "created": "2021-02-23T04:35:38+00:00",
                    "changed": "2021-02-23T04:35:38+00:00"
                },
                {
                    "id": "pl-2",
                    "name": "random - admin - public (admin)",
                    "owner": "admin",
                    "public": true,
                    "songCount": 43,
                    "duration": 17786,
                    "created": "2021-02-23T04:34:56+00:00",
                    "changed": "2021-02-23T04:34:56+00:00"
                },
                {
                    "id": "pl-4",
                    "name": "random - user - private",
                    "owner": "user",
                    "public": false,
                    "songCount": 43,
                    "duration": 17875,
                    "created": "2021-02-23T04:35:38+00:00",
                    "changed": "2021-02-23T04:35:38+00:00"
                },
                {
                    "id": "sp-19",
                    "name": "Song 1* (System)",
                    "owner": "System",
                    "public": true,
                    "songCount": 0,
                    "duration": 0,
                    "created": "1970-01-01T00:00:00+00:00",
                    "changed": "2025-07-01T05:51:53+00:00"
                },
                {
                    "id": "sp-18",
                    "name": "Song 2* (System)",
                    "owner": "System",
                    "public": true,
                    "songCount": 0,
                    "duration": 0,
                    "created": "1970-01-01T00:00:00+00:00",
                    "changed": "2025-07-01T05:51:53+00:00"
                },
                {
                    "id": "sp-17",
                    "name": "Song 3* (System)",
                    "owner": "System",
                    "public": true,
                    "songCount": 0,
                    "duration": 0,
                    "created": "1970-01-01T00:00:00+00:00",
                    "changed": "2025-07-01T05:51:53+00:00"
                },
                {
                    "id": "sp-16",
                    "name": "Song 4* (System)",
                    "owner": "System",
                    "public": true,
                    "songCount": 0,
                    "duration": 0,
                    "created": "1970-01-01T00:00:00+00:00",
                    "changed": "2025-07-01T05:51:53+00:00"
                },
                {
                    "id": "sp-15",
                    "name": "Song 5* (System)",
                    "owner": "System",
                    "public": true,
                    "songCount": 0,
                    "duration": 0,
                    "created": "1970-01-01T00:00:00+00:00",
                    "changed": "2025-07-01T05:51:53+00:00"
                },
                {
                    "id": "sp-20",
                    "name": "Unplayed by me (demo)",
                    "owner": "demo",
                    "public": true,
                    "songCount": 53,
                    "duration": 20669,
                    "created": "1970-01-01T00:00:00+00:00",
                    "changed": "2025-07-01T05:51:53+00:00"
                },
                {
                    "id": "sp-22",
                    "name": "user - 07/18/2024 11:54:12",
                    "owner": "user",
                    "public": true,
                    "songCount": 0,
                    "duration": 0,
                    "created": "1970-01-01T00:00:00+00:00",
                    "changed": "2025-07-01T05:51:53+00:00"
                }
            ]
        }
    }
}