[
    {
        "id": "19",
        "name": "Various Artists",
        "albums": [
            {
                "id": "12",
                "name": "Buried in Nausea",
                "artist": {
                    "id": "19",
                    "name": "Various Artists"
                },
                "time": 1879,
                "year": 2012,
                "tracks": 9,
                "songcount": 9,
                "type": "compilation",
                "disk": 1,
                "tag": [
                    {
                        "id": "7",
                        "name": "Punk"
                    }
                ],
                "art": "https:\/\/music.com.au\/image.php?object_id=12&object_type=album&auth=eeb9f1b6056246a7d563f479f518bb34",
                "flag": 0,
                "preciserating": null,
                "rating": null,
                "averagerating": null,
                "mbid": null
            }
        ],
        "albumcount": 1,
        "songs": 0,
        "songcount": 0,
        "tag": [],
        "art": "https:\/\/music.com.au\/image.php?object_id=19&object_type=artist&auth=eeb9f1b6056246a7d563f479f518bb34",
        "flag": 0,
        "preciserating": null,
        "rating": null,
        "averagerating": null,
        "mbid": "",
        "summary": "Warning! Deleting this artist may remove other artists and scrobbles from your library - please handle with caution!  Note: You can view albums tagged as 'Various Artists' in your library here. \n\nThe term Various Artists is used in the record industry when numerous singers and musicians collaborate on a song or collection of songs. Most often on Last.fm, compilation album tracks appear under the name of Various Artists erroneously because the individual artist is not listed in the album's ID3 information. ",
        "time": 1437,
        "yearformed": 0,
        "placeformed": ""
    }
]