{
    "session_expire": "2021-02-24T11:51:05+10:00",
    "server": "4.4.0-develop",
    "version": "440000",
    "compatible": "350001",
    "api": "440000",
    "update": "2021-02-23T14:24:54+10:00",
    "add": "2021-02-23T14:29:46+10:00",
    "clean": "2021-02-23T14:25:33+10:00",
    "songs": 53,
    "albums": 8,
    "artists": 14,
    "playlists": 19,
    "videos": 2,
    "catalogs": 4,
    "users": 8,
    "tags": 6,
    "podcasts": 2,
    "podcast_episodes": 13,
    "shares": 0,
    "licenses": 14,
    "live_streams": 3,
    "labels": 0
}