{
    "playlist": [
        {
            "id": "3",
            "name": "random - admin - private (admin)",
            "owner": "admin",
            "items": 43,
            "type": "private",
            "art": "https:\/\/music.com.au\/image.php?object_id=3&object_type=playlist&auth=eeb9f1b6056246a7d563f479f518bb34",
            "flag": 0,
            "preciserating": null,
            "rating": null,
            "averagerating": null
        },
        {
            "id": "2",
            "name": "random - admin - public (admin)",
            "owner": "admin",
            "items": 43,
            "type": "public",
            "art": "https:\/\/music.com.au\/image.php?object_id=2&object_type=playlist&auth=eeb9f1b6056246a7d563f479f518bb34",
            "flag": 1,
            "preciserating": null,
            "rating": null,
            "averagerating": null
        },
        {
            "id": "smart_21",
            "name": "admin - 02\/23\/2021 14:36:44 (admin)",
            "owner": "admin",
            "items": 5000,
            "type": "public",
            "art": "https:\/\/music.com.au\/image.php?object_id=21&object_type=search&auth=eeb9f1b6056246a7d563f479f518bb34",
            "flag": 0,
            "preciserating": null,
            "rating": null,
            "averagerating": null
        },
        {
            "id": "smart_14",
            "name": "Album 1* (System)",
            "owner": "System",
            "items": 2,
            "type": "public",
            "art": "https:\/\/music.com.au\/image.php?object_id=14&object_type=search&auth=eeb9f1b6056246a7d563f479f518bb34",
            "flag": 0,
            "preciserating": null,
            "rating": null,
            "averagerating": null
        }
    ]
}