[
    {
        "tag": [
            {
                "id": "1143",
                "name": "Brutal Death Metal",
                "albums": 10,
                "artists": 18,
                "songs": 333,
                "videos": 0,
                "playlists": 0,
                "stream": 0
            },
            {
                "id": "2750",
                "name": "Slamming Brutal Death Metal",
                "albums": 8,
                "artists": 1,
                "songs": 86,
                "videos": 0,
                "playlists": 0,
                "stream": 0
            }
        ]
    }
]