{
    "subsonic-response": {
        "status": "ok",
        "version": "1.16.1",
        "type": "ampache",
        "serverVersion": "6.8.0",
        "openSubsonic": true,
        "artistInfo": {
            "biography": "Nofi/found. is the work of Jeffrey Melton released prior to 2005. From the website:\nNofi is neither hi-fi nor lo-fi, but a state of being-without-boundaries (i.e. \u2019stateless\u2019).",
            "musicBrainzId": "",
            "smallImageUrl": "https://music.com.au/play/art/none/artist/14/size68x68.jpg",
            "mediumImageUrl": "https://music.com.au/play/art/none/artist/14/size128x128.jpg",
            "largeImageUrl": "https://music.com.au/play/art/none/artist/14/size348x348.jpg",
            "similarArtist": []
        }
    }
}